LICENSE
README.md
setup.py
webcam/__init__.py
webcam/_image_webcam.py
webcam/_perspective_manager.py
webcam/_video_recorder.py
webcam/_video_webcam.py
webcam/_webcam_background.py
webcam/webcam.py
webcam.egg-info/PKG-INFO
webcam.egg-info/SOURCES.txt
webcam.egg-info/dependency_links.txt
webcam.egg-info/requires.txt
webcam.egg-info/top_level.txt